ALLCools/__init__.py
ALLCools/__main__.py
ALLCools/_allc_to_bigwig.py
ALLCools/_allc_to_region_count.py
ALLCools/_bam_to_allc.py
ALLCools/_doc.py
ALLCools/_extract_allc.py
ALLCools/_merge_allc.py
ALLCools/_open.py
ALLCools/api.py
ALLCools/table_to_allc.py
ALLCools/utilities.py
ALLCools/abc/__init__.py
ALLCools/abc/abc_score.py
ALLCools/clustering/ClusterMerging.py
ALLCools/clustering/ConsensusClustering.py
ALLCools/clustering/__init__.py
ALLCools/clustering/art_of_tsne.py
ALLCools/clustering/balanced_pca.py
ALLCools/clustering/chromatin_conformation.py
ALLCools/clustering/dmg.py
ALLCools/clustering/incremental_pca.py
ALLCools/clustering/lsi.py
ALLCools/clustering/mcad.py
ALLCools/clustering/pvclust.py
ALLCools/clustering/rutilities.py
ALLCools/clustering/doublets/__init__.py
ALLCools/clustering/doublets/coverage_doublets.py
ALLCools/clustering/doublets/scrublet.py
ALLCools/clustering/feature_selection/__init__.py
ALLCools/clustering/feature_selection/feature_enrichment.py
ALLCools/clustering/feature_selection/gene_panel_design.py
ALLCools/count_matrix/__init__.py
ALLCools/count_matrix/atac.py
ALLCools/count_matrix/base_ds.py
ALLCools/count_matrix/dataset.py
ALLCools/count_matrix/h5ad.py
ALLCools/count_matrix/mcad.py
ALLCools/count_matrix/mcds.py
ALLCools/count_matrix/snap.py
ALLCools/count_matrix/zarr.py
ALLCools/dataset/__init__.py
ALLCools/dataset/dataset.yaml
ALLCools/dataset/directory_structure.py
ALLCools/dataset/entry_point.py
ALLCools/dmr/__init__.py
ALLCools/dmr/call_dmr.py
ALLCools/dmr/call_dmr_baseds.py
ALLCools/dmr/call_dms.py
ALLCools/dmr/call_dms_baseds.py
ALLCools/dmr/parse_methylpy.py
ALLCools/dmr/rms_test.py
ALLCools/genomic/__init__.py
ALLCools/gtf/Gtf.py
ALLCools/gtf/__init__.py
ALLCools/gtf/utilities.py
ALLCools/integration/__init__.py
ALLCools/integration/cca.py
ALLCools/integration/confusion.py
ALLCools/integration/metric.py
ALLCools/integration/seurat_class.py
ALLCools/jbrowse/__init__.py
ALLCools/mcds/__init__.py
ALLCools/mcds/base_ds.py
allcools-1.1.1.dist-info/entry_points.txt
allcools-1.1.1.dist-info/licenses/LICENSE
allcools-1.1.1.dist-info/WHEEL
allcools-1.1.1.dist-info/METADATA
allcools-1.1.1.dist-info/RECORD
